pycsvify/__init__.py
pycsvify/test.py
pycsvify-0.1.0.dist-info/LICENSE
pycsvify-0.1.0.dist-info/METADATA
pycsvify-0.1.0.dist-info/WHEEL
pycsvify-0.1.0.dist-info/top_level.txt
pycsvify-0.1.0.dist-info/RECORD
