Metadata-Version: 2.1
Name: pycsvify
Version: 0.1.0
Summary: A Python library that allows easy CSV to Dict conversion
Home-page: https://github.com/wesselmeijer/pycsvify
Author: Wessel Meijer
License: UNKNOWN
Platform: UNKNOWN
Classifier: Programming Language :: Python :: 3
Classifier: License :: OSI Approved :: MIT License
Classifier: Operating System :: OS Independent
